fasttext_reducer/__init__.py
fasttext_reducer/reduce_fasttext_models.py
fasttext_reducer-0.1.3.dist-info/LICENSE
fasttext_reducer-0.1.3.dist-info/METADATA
fasttext_reducer-0.1.3.dist-info/WHEEL
fasttext_reducer-0.1.3.dist-info/entry_points.txt
fasttext_reducer-0.1.3.dist-info/top_level.txt
fasttext_reducer-0.1.3.dist-info/RECORD
