Metadata-Version: 2.1
Name: fasttext_reducer
Version: 0.1.3
Summary: Lightweight package that allows for downloading fasttext models to any location and reducing their dimensions through a one-liner.
Author-email: Ramtin Yazdanian <ramtin.yazdanian@epfl.ch>
Project-URL: Homepage, https://github.com/RamtinYazdanian/fasttext-reducer
Project-URL: Bug Tracker, https://github.com/RamtinYazdanian/fasttext-reducer/issues
Classifier: Programming Language :: Python :: 3
Classifier: License :: OSI Approved :: MIT License
Classifier: Operating System :: OS Independent
Requires-Python: >=3.8
License-File: LICENSE
Requires-Dist: fasttext-wheel
